intfold/__init__.py
intfold/data/__init__.py
intfold/data/const.py
intfold/data/types.py
intfold/data/augmentation/__init__.py
intfold/data/augmentation/utils.py
intfold/data/crop/__init__.py
intfold/data/crop/boltz.py
intfold/data/crop/cropper.py
intfold/data/feature/__init__.py
intfold/data/feature/featurizer.py
intfold/data/feature/pad.py
intfold/data/feature/symmetry.py
intfold/data/filter/__init__.py
intfold/data/filter/dynamic/__init__.py
intfold/data/filter/dynamic/date.py
intfold/data/filter/dynamic/filter.py
intfold/data/filter/dynamic/max_residues.py
intfold/data/filter/dynamic/resolution.py
intfold/data/filter/dynamic/size.py
intfold/data/filter/dynamic/subset.py
intfold/data/filter/static/__init__.py
intfold/data/filter/static/filter.py
intfold/data/filter/static/ligand.py
intfold/data/filter/static/polymer.py
intfold/data/inference/__init__.py
intfold/data/inference/data_tools.py
intfold/data/inference/params.py
intfold/data/inference/utils.py
intfold/data/module/__init__.py
intfold/data/module/inference.py
intfold/data/module/training.py
intfold/data/msa/__init__.py
intfold/data/msa/mmseqs2.py
intfold/data/parse/__init__.py
intfold/data/parse/a3m.py
intfold/data/parse/csv.py
intfold/data/parse/fasta.py
intfold/data/parse/schema.py
intfold/data/parse/yaml.py
intfold/data/sample/__init__.py
intfold/data/sample/cluster.py
intfold/data/sample/distillation.py
intfold/data/sample/random.py
intfold/data/sample/sampler.py
intfold/data/tokenize/__init__.py
intfold/data/tokenize/boltz.py
intfold/data/tokenize/tokenizer.py
intfold/data/write/__init__.py
intfold/data/write/mmcif.py
intfold/data/write/pdb.py
intfold/data/write/utils.py
intfold/data/write/writer.py
intfold/openfold/__init__.py
intfold/openfold/config.py
intfold/openfold/inference_config.py
intfold/openfold/model/__init__.py
intfold/openfold/model/backbone.py
intfold/openfold/model/confidences.py
intfold/openfold/model/diffusion.py
intfold/openfold/model/dropout.py
intfold-0.1.4.dist-info/LICENSE
intfold-0.1.4.dist-info/METADATA
intfold-0.1.4.dist-info/WHEEL
intfold-0.1.4.dist-info/entry_points.txt
intfold-0.1.4.dist-info/top_level.txt
intfold-0.1.4.dist-info/RECORD
